wsgitalkback/__init__.py
wsgitalkback/app.py
wsgitalkback/cookie.py
wsgitalkback/dbkeeper.py
wsgitalkback/formdata.py
wsgitalkback/fskeeper.py
wsgitalkback/loader.py
wsgitalkback/parse.py
wsgitalkback/path.py
wsgitalkback/responder.py
wsgitalkback/session.py
wsgitalkback/transport.py
wsgitalkback-1.4.dist-info/METADATA
wsgitalkback-1.4.dist-info/WHEEL
wsgitalkback-1.4.dist-info/top_level.txt
wsgitalkback-1.4.dist-info/RECORD
