Metadata-Version: 2.1
Name: wsgitalkback
Version: 1.4
Summary: A responder framework to write responders to url requests, implements RFC 2616,RFC 2965
Home-page: http://www.github.com/madhukumarseshadri
Author: Madhukumar Seshadri
Author-email: madhukumarseshadri@gmail.com
License: MIT License
Platform: any
Classifier: Development Status :: 5 - Production/Stable
Classifier: Environment :: Web Environment
Classifier: Intended Audience :: Developers
Classifier: License :: OSI Approved :: Apache Software License
Classifier: Operating System :: OS Independent
Classifier: Programming Language :: Python
Classifier: Topic :: Internet :: WWW/HTTP :: Dynamic Content
Classifier: Topic :: Software Development :: Libraries :: Python Modules
